rufffmt/__init__.py
rufffmt/__main__.py
rufffmt/__version__.py
rufffmt/cli.py
rufffmt/core.py
rufffmt/lsp.py
rufffmt/tests/__init__.py
rufffmt/tests/__main__.py
rufffmt/tests/core.py
rufffmt-1.0.dist-info/entry_points.txt
rufffmt-1.0.dist-info/LICENSE
rufffmt-1.0.dist-info/WHEEL
rufffmt-1.0.dist-info/METADATA
rufffmt-1.0.dist-info/RECORD
